protoyang/__init__.py
protoyang/merge_proto_module.py
protoyang/proto_writer.py
protoyang/translate_yang2proto.py
protoyang/yang_util.py
protoyang/hpproto/__init__.py
protoyang/hpproto/proto_parse.py
protoyang/hpproto/proto_proto.py
protoyang/hpproto/syntax.py
src/__init__.py
src/merge_proto_module.py
src/proto_writer.py
src/translate_yang2proto.py
src/yang_util.py
src/hpproto/__init__.py
src/hpproto/proto_parse.py
src/hpproto/proto_proto.py
src/hpproto/syntax.py
protoyang-0.0.2.dist-info/LICENSE
protoyang-0.0.2.dist-info/METADATA
protoyang-0.0.2.dist-info/WHEEL
protoyang-0.0.2.dist-info/top_level.txt
protoyang-0.0.2.dist-info/RECORD
