Metadata-Version: 2.1
Name: protoyang
Version: 0.0.2
Summary: a tool generate .proto files according yang modules
Home-page: https://github.com/HuaweiDatacomm/protoyang
Author: feng chong
Author-email: frank.fengchong@huawei.com
License: Apache License, Version 2.0
Platform: UNKNOWN
